tgpolls
