Metadata-Version: 1.0
Name: tgapp-tgpolls
Version: 0.0.5
Summary: UNKNOWN
Home-page: UNKNOWN
Author: Puria Nafisi Azizi
Author-email: puria.nafisi@axant.it
License: UNKNOWN
Keywords: turbogears2.application
Platform: UNKNOWN
